MORALS/__init__.py
MORALS/data_utils.py
MORALS/dynamics_utils.py
MORALS/grid.py
MORALS/mg_utils.py
MORALS/models.py
MORALS/training.py
MORALS/systems/N_CML.py
MORALS/systems/__init__.py
MORALS/systems/bistable.py
MORALS/systems/bistable_rot.py
MORALS/systems/cartpole.py
MORALS/systems/humanoid.py
MORALS/systems/leslie_map.py
MORALS/systems/ndpendulum.py
MORALS/systems/pendulum.py
MORALS/systems/pendulum3links.py
MORALS/systems/system.py
MORALS/systems/trifinger.py
MORALS/systems/unifinger.py
MORALS/systems/utils.py
MORALS-0.1.4.dist-info/LICENSE
MORALS-0.1.4.dist-info/METADATA
MORALS-0.1.4.dist-info/WHEEL
MORALS-0.1.4.dist-info/top_level.txt
MORALS-0.1.4.dist-info/RECORD
